{
    "art pop": [
        "5gspAQIAH8nJUrMYgXjCJ2"
    ],
    "chamber pop": [
        "5gspAQIAH8nJUrMYgXjCJ2"
    ],
    "indie rock": [
        "5gspAQIAH8nJUrMYgXjCJ2"
    ],
    "modern folk rock": [
        "5gspAQIAH8nJUrMYgXjCJ2",
        "1MK90Dn9tMbk16g2Vb2NQp"
    ],
    "neo-psychedelic": [
        "5gspAQIAH8nJUrMYgXjCJ2"
    ],
    "noise pop": [
        "5gspAQIAH8nJUrMYgXjCJ2"
    ],
    "philly indie": [
        "5gspAQIAH8nJUrMYgXjCJ2"
    ],
    "singer-songwriter": [
        "5gspAQIAH8nJUrMYgXjCJ2"
    ],
    "psicodelia brasileira": [
        "30RyGMjuSYBfHRQF3oANq7"
    ],
    "alternative hip hop": [
        "3A5tHz1SfngyOZM2gItYKu"
    ],
    "drumless hip hop": [
        "3A5tHz1SfngyOZM2gItYKu"
    ],
    "experimental hip hop": [
        "3A5tHz1SfngyOZM2gItYKu"
    ],
    "hip hop": [
        "3A5tHz1SfngyOZM2gItYKu"
    ],
    "rap": [
        "3A5tHz1SfngyOZM2gItYKu"
    ],
    "underground hip hop": [
        "3A5tHz1SfngyOZM2gItYKu"
    ],
    "italian adult pop": [
        "582KhTHEVOONNQLmQ5612r",
        "2caOYPej26UoQOyFnzXW3G"
    ],
    "italian pop": [
        "582KhTHEVOONNQLmQ5612r"
    ],
    "rome indie": [
        "582KhTHEVOONNQLmQ5612r"
    ],
    "french psychedelic": [
        "2Gq1u66tc99HT0wnA3mj1W"
    ],
    "psychedelic pop": [
        "2Gq1u66tc99HT0wnA3mj1W"
    ],
    "canzone d'autore": [
        "2caOYPej26UoQOyFnzXW3G"
    ],
    "classic italian pop": [
        "2caOYPej26UoQOyFnzXW3G"
    ],
    "garage psych": [
        "1MK90Dn9tMbk16g2Vb2NQp"
    ],
    "montreal indie": [
        "10tvYvaoSO32hlvu3NrrPC"
    ]
}